{
  "group": "porkys_betterminecraft",
  "type": "minecraft:crafting_shaped",
  "pattern": [
    " 1 ",
    "345",
    " 7 "
  ],
  "key": {
    "1": {
      "item": "porkys_betterminecraft:meat_gem"
    },
    "3": {
      "item": "porkys_betterminecraft:meat_gem"
    },
    "4": {
      "item": "minecraft:gold_ingot"
    },
    "5": {
      "item": "porkys_betterminecraft:meat_gem"
    },
    "7": {
      "item": "porkys_betterminecraft:meat_gem"
    }
  },
  "result": {
    "item": "porkys_betterminecraft:pig_dimension",
    "count": 1
  }
}